Metadata-Version: 1.1
Name: fidentify
Version: 1.0.0
Summary: Python Script to identify faces in a video. It is a ready-to-run code! 
Home-page: https://github.com/NoSkillGuy/fidentify
Author: Siva Praveen Rayapudi
Author-email: rsivapraveen001@gmail.com
License: MIT
Download-URL: https://github.com/NoSkillGuy/fidentify/tarball/1.0.0
Keywords: face-recognition face-detection face detection recognition terminal command-line work
Platform: UNKNOWN
Classifier: Development Status :: 4 - Beta
Classifier: Intended Audience :: Developers
Classifier: License :: OSI Approved :: MIT License
Classifier: Programming Language :: Python :: 2.7
Classifier: Programming Language :: Python :: 3.3
Classifier: Programming Language :: Python :: 3.4
Classifier: Programming Language :: Python :: 3.5
Classifier: Programming Language :: Python :: 3.6
